miceless/__init__.py
miceless/run.py
miceless/state.py
miceless-1.0.0.dist-info/LICENSE
miceless-1.0.0.dist-info/METADATA
miceless-1.0.0.dist-info/WHEEL
miceless-1.0.0.dist-info/top_level.txt
miceless-1.0.0.dist-info/RECORD
