Metadata-Version: 2.1
Name: miceless
Version: 1.0.0
Summary: Hotkeys for mouse click events.
Home-page: https://github.com/akademi4eg/miceless
Maintainer: Dmytro Tkanov
Maintainer-email: akademi4eg@gmail.com
License: Apache License 2.0
Platform: UNKNOWN
Classifier: Programming Language :: Python :: 3
Classifier: License :: OSI Approved :: Apache Software License
Classifier: Operating System :: POSIX :: Linux
Classifier: Environment :: X11 Applications
Classifier: Intended Audience :: End Users/Desktop
Classifier: Topic :: Utilities
Requires-Dist: pynput (==1.4)
